README.rst
setup.py
easystore/__init__.py
easystore.egg-info/PKG-INFO
easystore.egg-info/SOURCES.txt
easystore.egg-info/dependency_links.txt
easystore.egg-info/top_level.txt