Metadata-Version: 1.1
Name: easystore
Version: 1.3.4
Summary: Redis like syntax to store and retrieve from json files
Home-page: https://github.com/shomiron/easystore
Author: Shomiron DAS GUPTA
Author-email: shomiron@netmonastery.com
License: Apache
Keywords: redis,json
Platform: UNKNOWN
Classifier: Development Status :: 4 - Beta
Classifier: Intended Audience :: Developers
Classifier: Topic :: Software Development :: Libraries :: Python Modules
Classifier: License :: OSI Approved :: Apache Software License
Classifier: Programming Language :: Python
Classifier: Programming Language :: Python :: 2.6
Classifier: Programming Language :: Python :: 2.7
Classifier: Programming Language :: Python :: 3.3
